{
  "api_name": "organization",
  "method": "POST",
  "path": "/organizationalStructure/queryOrganizationNumber",
  "payload": {
    "projectId": "71a7020a062642a888f9e85a0a29e141",
    "pageNo": 1,
    "pageSize": 200
  },
  "project_id": "71a7020a062642a888f9e85a0a29e141",
  "result": {
    "code": 0,
    "message": "查询自有人员信息列表成功！",
    "data": [
      {
        "id": "f14731a2956442589bb8a15251b4363e",
        "projectId": "71a7020a062642a888f9e85a0a29e141",
        "employeeId": "10121292",
        "employeeName": "杜雨萌",
        "department": "体系数字化规划部",
        "departmentId": "27",
        "postId": "7cdd53247e6446a0ab6c0c580fc7bf0b",
        "postName": "前后端开发工程师",
        "rank": "T6",
        "rankId": null,
        "manDay": "47",
        "maintenanceName": null,
        "maintenanceId": null,
        "contractId": null,
        "price": null,
        "priceTax": null,
        "unitPrice": null,
        "unitPriceTax": null,
        "numberPeople": null,
        "flag": 0,
        "numberList": null,
        "maxValue": "10",
        "minValue": "0",
        "meetingId": null,
        "workContent": null,
        "score": null,
        "taskDescription": null,
        "peopleBelong": null,
        "teamId": "1fe60f1603854dbc950150dbaba9afd8",
        "teamName": "COM08小队",
        "productName": null,
        "modelVersion": null,
        "type": null,
        "planStartDate": "2025-10-15",
        "planEndDate": "2025-11-30",
        "sumBudget": null,
        "projectName": null,
        "taxRate": null
      },
      {
        "id": "5b4880c878fc404594db5ee0c69b5dd0",
        "projectId": "71a7020a062642a888f9e85a0a29e141",
        "employeeId": "10248717",
        "employeeName": "刘怡童",
        "department": "体系数字化规划部",
        "departmentId": "27",
        "postId": "7cdd53247e6446a0ab6c0c580fc7bf0b",
        "postName": "前后端开发工程师",
        "rank": "T4",
        "rankId": null,
        "manDay": "47",
        "maintenanceName": null,
        "maintenanceId": null,
        "contractId": null,
        "price": null,
        "priceTax": null,
        "unitPrice": null,
        "unitPriceTax": null,
        "numberPeople": null,
        "flag": 0,
        "numberList": null,
        "maxValue": "10",
        "minValue": "0",
        "meetingId": null,
        "workContent": null,
        "score": null,
        "taskDescription": null,
        "peopleBelong": null,
        "teamId": "1fe60f1603854dbc950150dbaba9afd8",
        "teamName": "COM08小队",
        "productName": null,
        "modelVersion": null,
        "type": null,
        "planStartDate": "2025-10-15",
        "planEndDate": "2025-11-30",
        "sumBudget": null,
        "projectName": null,
        "taxRate": null
      }
    ]
  },
  "error": "",
  "called_at": "2026-03-18T08:52:27+08:00"
}