{
  "api_name": "tam_info",
  "method": "GET",
  "path": "/value/info/5a4f8458b48943b6a2a667738dbe1666",
  "payload": null,
  "project_id": "5a4f8458b48943b6a2a667738dbe1666",
  "result": {
    "code": 0,
    "message": "操作成功",
    "data": {
      "1": {
        "id": 488,
        "projectId": "5a4f8458b48943b6a2a667738dbe1666",
        "isInvolve": 0,
        "projectValueInfoList": [
          {
            "id": 1195,
            "projectId": "5a4f8458b48943b6a2a667738dbe1666",
            "projectValueId": 488,
            "title": "",
            "valueGoal": null,
            "currentStatus": "",
            "deptId": "[]",
            "oneKey": 2025,
            "oneValue": "",
            "twoValue": "",
            "threeValue": "",
            "content": "",
            "creatorId": null,
            "creator": null,
            "createTime": null,
            "modifierId": null,
            "modifier": null,
            "updateTime": null,
            "isDelete": 0,
            "type": 1,
            "actualTargetYear": null,
            "actualTargetText": null,
            "oneValueActual": null,
            "twoValueActual": null,
            "threeValueActual": null
          }
        ],
        "creatorId": null,
        "creator": null,
        "createTime": "2025-09-28 11:07:03",
        "modifierId": null,
        "modifier": null,
        "updateTime": "2025-10-30 14:55:37",
        "isDelete": 0,
        "type": 1,
        "isAccept": null
      },
      "2": {
        "id": 489,
        "projectId": "5a4f8458b48943b6a2a667738dbe1666",
        "isInvolve": 0,
        "projectValueInfoList": [
          {
            "id": 1196,
            "projectId": "5a4f8458b48943b6a2a667738dbe1666",
            "projectValueId": 489,
            "title": "",
            "valueGoal": null,
            "currentStatus": "",
            "deptId": "[]",
            "oneKey": 2025,
            "oneValue": "",
            "twoValue": "",
            "threeValue": "",
            "content": "",
            "creatorId": null,
            "creator": null,
            "createTime": null,
            "modifierId": null,
            "modifier": null,
            "updateTime": null,
            "isDelete": 0,
            "type": 2,
            "actualTargetYear": null,
            "actualTargetText": null,
            "oneValueActual": null,
            "twoValueActual": null,
            "threeValueActual": null
          }
        ],
        "creatorId": null,
        "creator": null,
        "createTime": "2025-09-28 11:07:03",
        "modifierId": null,
        "modifier": null,
        "updateTime": "2025-10-30 14:55:37",
        "isDelete": 0,
        "type": 2,
        "isAccept": null
      },
      "3": {
        "id": 490,
        "projectId": "5a4f8458b48943b6a2a667738dbe1666",
        "isInvolve": 1,
        "projectValueInfoList": [
          {
            "id": 1197,
            "projectId": "5a4f8458b48943b6a2a667738dbe1666",
            "projectValueId": 490,
            "title": "印章管理上线率",
            "valueGoal": null,
            "currentStatus": "线下管理",
            "deptId": "[\"1\",\"2\",\"3\",\"4\",\"5\",\"6\",\"7\",\"8\",\"191\",\"192\",\"12\",\"193\",\"208\"]",
            "oneKey": 2025,
            "oneValue": "90%",
            "twoValue": "100%",
            "threeValue": "100%",
            "content": "印章上线率",
            "creatorId": null,
            "creator": null,
            "createTime": null,
            "modifierId": null,
            "modifier": null,
            "updateTime": null,
            "isDelete": 0,
            "type": 3,
            "actualTargetYear": null,
            "actualTargetText": null,
            "oneValueActual": null,
            "twoValueActual": null,
            "threeValueActual": null
          }
        ],
        "creatorId": null,
        "creator": null,
        "createTime": "2025-09-28 11:07:03",
        "modifierId": null,
        "modifier": null,
        "updateTime": "2025-10-30 14:55:37",
        "isDelete": 0,
        "type": 3,
        "isAccept": null
      }
    }
  },
  "error": "",
  "called_at": "2026-03-16T10:54:41+08:00"
}