{
  "api_name": "cost_change",
  "method": "GET",
  "path": "/change/list/79eac664f436488993cb28eaac1cc996",
  "payload": null,
  "project_id": "79eac664f436488993cb28eaac1cc996",
  "result": {
    "code": 0,
    "message": "操作成功",
    "data": [
      {
        "id": 471,
        "projectId": "79eac664f436488993cb28eaac1cc996",
        "isChange": 1,
        "dimensionality": "3",
        "oneKey": "2024年",
        "oneValue": null,
        "twoKey": "2025年",
        "twoValue": null,
        "threeKey": "2026年",
        "threeValue": null,
        "creatorId": 87864,
        "creator": "fengdalong",
        "createTime": "2026-03-09 14:59:48",
        "modifierId": null,
        "modifier": null,
        "updateTime": null,
        "isDelete": 0,
        "oneTwoSymbol": null,
        "oneTwoValue": null,
        "twoThreeSymbol": null,
        "twoThreeValue": null,
        "dimensionalityName": "费用成本",
        "content": null
      }
    ]
  },
  "error": "",
  "called_at": "2026-03-16T10:49:13+08:00"
}